[1,["4aYInTqrFJBI9abj6AtlDr","b8eigFtHtIvIJ2wugg2OJS","281gRWem1IMqIcys5JvEng","320W57HiNDvrI6shYFADcN","2aWY34ogdAhbYVNDypg/NL","1bt5Uh6apJPLb+0SWK5P8Y","e3ER5XU+xOPpoLdg+Nj3hk","0e0nddMyNPGbrqge7ye8xA","ffL1f5jalMxZ1+A1Zic5jM","81McsT8c1Hp7KhImvAn/CA","b5VHysJtFGs5X/YYIemCxH","c2lYGf7jhFN7sdGJBxfe1U","f4qw2yMPBF5aiHJ4jmeC+d","89om0gWphE2ZzV2zWVS1eA","b8YqZt07NMX4+5+1scVvhi","0dRk41e8hGNbQMACNq/OR/","115wJ3dylLIqm76NGPvWNC","2bCyGz8O1KWbqEp6/HWNb/","fcA+Px4FtEX5KzUvm+EVEO","dfPIcHujNP3ICF6hjcIjBP","7aNKIc1rhIHpKQ8Keqh2gS","d4KLA+RYZFDqu4SuohN7qO","87RTDusPhAG4x24cYAaht5","97yHhgnV9Gqre8tVKFzc2W","b8TAm+MRhISJ/yteUe7/RX","d9t/rDE/9CF687ZOdoMz+s"],["_textureSetter","Casino_C_huangse_10c","Casino_C_huangse_1c","Casino_C_huangse_2c","Casino_C_huangse_5c","Casino_C_kuang_1","Casino_C_lvse_10c","Casino_C_lvse_1c","Casino_C_lvse_2c","Casino_C_lvse_5c","Casino_C_huangse_10c_2","Casino_C_huangse_10c_3","Casino_C_huangse_1c_2","Casino_C_huangse_1c_3","Casino_C_huangse_2c_2","Casino_C_huangse_2c_3","Casino_C_huangse_5c_2","Casino_C_huangse_5c_3","Casino_C_lvse_10c_2","Casino_C_lvse_10c_3","Casino_C_lvse_1c_2","Casino_C_lvse_1c_3","Casino_C_lvse_2c_2","Casino_C_lvse_2c_3","Casino_C_lvse_5c_2","Casino_C_lvse_5c_3"],["cc.SpriteFrame",["cc.SpriteAtlas",["_name","_spriteFrames"],2,11]],[[1,0,1,2]],[[[{"name":"Casino_C_huangse_2c_3","rect":[106,761,76,79],"offset":[0,0],"originalSize":[76,79],"capInsets":[0,0,0,0]}],[0],0,[0],[0],[0]],[[{"name":"Casino_C_lvse_1c","rect":[10,860,76,79],"offset":[0,0],"originalSize":[76,79],"capInsets":[0,0,0,0]}],[0],0,[0],[0],[0]],[[{"name":"Casino_C_huangse_5c_2","rect":[106,860,76,79],"offset":[0,0],"originalSize":[76,79],"capInsets":[0,0,0,0]}],[0],0,[0],[0],[0]],[[{"name":"Casino_C_kuang_1","rect":[10,10,94,335],"offset":[0,0],"originalSize":[94,335],"capInsets":[0,0,0,0]}],[0],0,[0],[0],[0]],[[{"name":"Casino_C_huangse_1c","rect":[10,464,76,79],"offset":[0,0],"originalSize":[76,79],"capInsets":[0,0,0,0]}],[0],0,[0],[0],[0]],[[{"name":"Casino_C_huangse_5c","rect":[10,662,76,79],"offset":[0,0],"originalSize":[76,79],"capInsets":[0,0,0,0]}],[0],0,[0],[0],[0]],[[{"name":"Casino_C_huangse_5c_3","rect":[202,307,76,79],"offset":[0,0],"originalSize":[76,79],"capInsets":[0,0,0,0]}],[0],0,[0],[0],[0]],[[{"name":"Casino_C_huangse_2c","rect":[10,563,76,79],"offset":[0,0],"originalSize":[76,79],"capInsets":[0,0,0,0]}],[0],0,[0],[0],[0]],[[{"name":"Casino_C_lvse_1c_2","rect":[220,208,76,79],"offset":[0,0],"originalSize":[76,79],"capInsets":[0,0,0,0]}],[0],0,[0],[0],[0]],[[{"name":"Casino_C_lvse_5c","rect":[124,10,76,79],"offset":[0,0],"originalSize":[76,79],"capInsets":[0,0,0,0]}],[0],0,[0],[0],[0]],[[{"name":"Casino_C_lvse_2c_2","rect":[202,505,76,79],"offset":[0,0],"originalSize":[76,79],"capInsets":[0,0,0,0]}],[0],0,[0],[0],[0]],[[{"name":"Casino_C_huangse_1c_3","rect":[106,563,76,79],"offset":[0,0],"originalSize":[76,79],"capInsets":[0,0,0,0]}],[0],0,[0],[0],[0]],[[{"name":"Casino_C_lvse_2c_3","rect":[202,604,76,79],"offset":[0,0],"originalSize":[76,79],"capInsets":[0,0,0,0]}],[0],0,[0],[0],[0]],[[[0,"CasinoDaFUQJ.plist",[{},"Casino_C_huangse_10c",6,0,"Casino_C_huangse_1c",6,1,"Casino_C_huangse_2c",6,2,"Casino_C_huangse_5c",6,3,"Casino_C_kuang_1",6,4,"Casino_C_lvse_10c",6,5,"Casino_C_lvse_1c",6,6,"Casino_C_lvse_2c",6,7,"Casino_C_lvse_5c",6,8,"Casino_C_huangse_10c_2",6,9,"Casino_C_huangse_10c_3",6,10,"Casino_C_huangse_1c_2",6,11,"Casino_C_huangse_1c_3",6,12,"Casino_C_huangse_2c_2",6,13,"Casino_C_huangse_2c_3",6,14,"Casino_C_huangse_5c_2",6,15,"Casino_C_huangse_5c_3",6,16,"Casino_C_lvse_10c_2",6,17,"Casino_C_lvse_10c_3",6,18,"Casino_C_lvse_1c_2",6,19,"Casino_C_lvse_1c_3",6,20,"Casino_C_lvse_2c_2",6,21,"Casino_C_lvse_2c_3",6,22,"Casino_C_lvse_5c_2",6,23,"Casino_C_lvse_5c_3",6,24]]],0,0,[0,0,0,0,0,0,0,0,0,0,0,0,0,0,0,0,0,0,0,0,0,0,0,0,0],[1,2,3,4,5,6,7,8,9,10,11,12,13,14,15,16,17,18,19,20,21,22,23,24,25],[1,2,3,4,5,6,7,8,9,10,11,12,13,14,15,16,17,18,19,20,21,22,23,24,25]],[[{"name":"Casino_C_huangse_10c_2","rect":[124,109,76,79],"offset":[0,0],"originalSize":[76,79],"capInsets":[0,0,0,0]}],[0],0,[0],[0],[0]],[[{"name":"Casino_C_lvse_5c_2","rect":[202,703,76,79],"offset":[0,0],"originalSize":[76,79],"capInsets":[0,0,0,0]}],[0],0,[0],[0],[0]],[[{"name":"Casino_C_huangse_2c_2","rect":[106,662,76,79],"offset":[0,0],"originalSize":[76,79],"capInsets":[0,0,0,0]}],[0],0,[0],[0],[0]],[[{"name":"Casino_C_huangse_10c","rect":[10,365,76,79],"offset":[0,0],"originalSize":[76,79],"capInsets":[0,0,0,0]}],[0],0,[0],[0],[0]],[[{"name":"Casino_C_huangse_10c_3","rect":[124,208,76,79],"offset":[0,0],"originalSize":[76,79],"capInsets":[0,0,0,0]}],[0],0,[0],[0],[0]],[[{"name":"Casino_C_lvse_1c_3","rect":[202,406,76,79],"offset":[0,0],"originalSize":[76,79],"capInsets":[0,0,0,0]}],[0],0,[0],[0],[0]],[[{"name":"Casino_C_lvse_5c_3","rect":[202,802,76,79],"offset":[0,0],"originalSize":[76,79],"capInsets":[0,0,0,0]}],[0],0,[0],[0],[0]],[[{"name":"Casino_C_lvse_10c_3","rect":[220,109,76,79],"offset":[0,0],"originalSize":[76,79],"capInsets":[0,0,0,0]}],[0],0,[0],[0],[0]],[[{"name":"Casino_C_lvse_10c","rect":[10,761,76,79],"offset":[0,0],"originalSize":[76,79],"capInsets":[0,0,0,0]}],[0],0,[0],[0],[0]],[[{"name":"Casino_C_huangse_1c_2","rect":[106,464,76,79],"offset":[0,0],"originalSize":[76,79],"capInsets":[0,0,0,0]}],[0],0,[0],[0],[0]],[[{"name":"Casino_C_lvse_10c_2","rect":[220,10,76,79],"offset":[0,0],"originalSize":[76,79],"capInsets":[0,0,0,0]}],[0],0,[0],[0],[0]],[[{"name":"Casino_C_lvse_2c","rect":[106,365,76,79],"offset":[0,0],"originalSize":[76,79],"capInsets":[0,0,0,0]}],[0],0,[0],[0],[0]]]]